{
    "collection": "riyadussalihin",
    "bookNumber": "introduction",
    "chapterId": "36.00",
    "hadithNumber": "293",
    "hadith": [
        {
            "lang": "en",
            "chapterNumber": "36",
            "chapterTitle": "Sustentation of the Members of the Family",
            "urn": 1602900,
            "body": "<p>Abu Mas'ud Al-Badri (May Allah be pleased with him) reported: The Prophet (\ufdfa) said, \"When someone spends on his family seeking his reward for it from Allah, it is counted as a charity from him\".<br/><br/><b>[Al-Bukhari and Muslim]</b>.<br/><br/></p>",
            "grades": []
        },
        {
            "lang": "ar",
            "chapterNumber": "36",
            "chapterTitle": "- \u0628\u0627\u0628 \u0627\u0644\u0646\u0641\u0642\u0629 \u0639\u0644\u0649 \u0627\u0644\u0639\u064a\u0627\u0644",
            "urn": 1702920,
            "body": "<p>- \u0648\u0639\u0646 \u0623\u0628\u064a \u0645\u0633\u0639\u0648\u062f \u0627\u0644\u0628\u062f\u0631\u064a \u0631\u0636\u064a \u0627\u0644\u0644\u0647 \u0639\u0646\u0647\u060c \u0639\u0646 \u0627\u0644\u0646\u0628\u064a \u0635\u0644\u0649 \u0627\u0644\u0644\u0647 \u0639\u0644\u064a\u0647 \u0648\u0633\u0644\u0645 \u0642\u0627\u0644\u200f:\u200f \u200f\"\u200f \u0625\u0630\u0627 \u0623\u0646\u0641\u0642 \u0627\u0644\u0631\u062c\u0644 \u0639\u0644\u0649 \u0623\u0647\u0644\u0647 \u0646\u0641\u0642\u0629 \u064a\u062d\u062a\u0633\u0628\u0647\u0627 \u0641\u0647\u064a \u0644\u0647 \u0635\u062f\u0642\u0629\u200f\"\u200f \u200f(\u200f\u200f(\u200f\u0645\u062a\u0641\u0642 \u0639\u0644\u064a\u0647\u200f)\u200f\u200f)\u200f\u200f.\u200f</p>",
            "grades": []
        }
    ]
}